{
	"info": {
		"_postman_id": "aa04d2b6-2798-49b3-a318-cf1c99bd86af",
		"name": "Authenticate",
		"schema": "https://schema.getpostman.com/json/collection/v2.1.0/collection.json",
		"_exporter_id": "15950439"
	},
	"item": [
		{
			"name": "update-password",
			"item": [
				{
					"name": "user-request-new-password",
					"request": {
						"method": "POST",
						"header": [
							{
								"key": "Authorization",
								"value": "",
								"type": "text"
							}
						],
						"url": {
							"raw": "localhost:3333/user/request/new-password",
							"host": [
								"localhost"
							],
							"port": "3333",
							"path": [
								"user",
								"request",
								"new-password"
							]
						}
					},
					"response": []
				},
				{
					"name": "user-update-password",
					"request": {
						"method": "POST",
						"header": [
							{
								"key": "Authorization",
								"value": "",
								"type": "text"
							}
						],
						"body": {
							"mode": "raw",
							"raw": "{\r\n    \"password\": \"Test3@\",\r\n    \"confirmPassword\": \"Test3@\",\r\n    \"token\": \"28297\"\r\n}",
							"options": {
								"raw": {
									"language": "json"
								}
							}
						},
						"url": {
							"raw": "localhost:3333/user/request/update-password",
							"host": [
								"localhost"
							],
							"port": "3333",
							"path": [
								"user",
								"request",
								"update-password"
							]
						}
					},
					"response": []
				}
			]
		},
		{
			"name": "update-email",
			"item": [
				{
					"name": "user-request-new-email",
					"request": {
						"method": "POST",
						"header": [
							{
								"key": "Authorization",
								"value": "",
								"type": "text"
							}
						],
						"body": {
							"mode": "raw",
							"raw": "{\r\n    \"email\": \"test@hotmail.com\",\r\n    \"id\": 8\r\n}",
							"options": {
								"raw": {
									"language": "json"
								}
							}
						},
						"url": {
							"raw": "localhost:3333/auth/new-email",
							"host": [
								"localhost"
							],
							"port": "3333",
							"path": [
								"auth",
								"new-email"
							]
						}
					},
					"response": []
				},
				{
					"name": "user-update-email",
					"request": {
						"method": "POST",
						"header": [
							{
								"key": "Authorization",
								"value": "",
								"type": "text"
							}
						],
						"body": {
							"mode": "raw",
							"raw": "{\r\n    \"email\": \"test@hotmail.com\",\r\n    \"id\": 10\r\n}",
							"options": {
								"raw": {
									"language": "json"
								}
							}
						},
						"url": {
							"raw": "localhost:3333/auth/new-email/92737",
							"host": [
								"localhost"
							],
							"port": "3333",
							"path": [
								"auth",
								"new-email",
								"92737"
							]
						}
					},
					"response": []
				}
			]
		},
		{
			"name": "user-create",
			"request": {
				"method": "POST",
				"header": [],
				"body": {
					"mode": "raw",
					"raw": "{\r\n    \"email\": \"test4@hotmail.com\",\r\n    \"password\": \"@Delas1\"\r\n}",
					"options": {
						"raw": {
							"language": "json"
						}
					}
				},
				"url": {
					"raw": "localhost:3333/user/create",
					"host": [
						"localhost"
					],
					"port": "3333",
					"path": [
						"user",
						"create"
					]
				}
			},
			"response": []
		},
		{
			"name": "user-complet",
			"request": {
				"method": "POST",
				"header": [],
				"body": {
					"mode": "raw",
					"raw": "{\r\n    \"email\": \"test4@hotmail.com\",\r\n    \"password\": \"@Delas1\"\r\n}",
					"options": {
						"raw": {
							"language": "json"
						}
					}
				},
				"url": {
					"raw": "localhost:3333/user/create",
					"host": [
						"localhost"
					],
					"port": "3333",
					"path": [
						"user",
						"create"
					]
				}
			},
			"response": []
		},
		{
			"name": "user-login",
			"request": {
				"method": "POST",
				"header": [],
				"body": {
					"mode": "raw",
					"raw": "{\r\n    \"email\": \"test4@hotmail.com\",\r\n    \"password\": \"@Delas1\"\r\n}",
					"options": {
						"raw": {
							"language": "json"
						}
					}
				},
				"url": {
					"raw": "localhost:3333/user/create",
					"host": [
						"localhost"
					],
					"port": "3333",
					"path": [
						"user",
						"create"
					]
				}
			},
			"response": []
		}
	]
}
